leeselab_project_creator/__init__.py
leeselab_project_creator/__main__.py
leeselab_project_creator/generate_plate_layout.py
leeselab_project_creator/generate_worklist.py
leeselab_project_creator-2.0.0.dist-info/licenses/LICENSE
leeselab_project_creator-2.0.0.dist-info/METADATA
leeselab_project_creator-2.0.0.dist-info/WHEEL
leeselab_project_creator-2.0.0.dist-info/entry_points.txt
leeselab_project_creator-2.0.0.dist-info/top_level.txt
leeselab_project_creator-2.0.0.dist-info/RECORD
