Metadata-Version: 2.4
Name: leeselab-project-creator
Version: 2.0.0
Summary: The leeselab project creator.
Home-page: https://github.com/DominikBuchner/BOLDigger-commandline
Author: Dominik Buchner
Author-email: dominik.buchner524@googlemail.com
License: MIT
Classifier: Programming Language :: Python :: 3
Classifier: License :: OSI Approved :: MIT License
Classifier: Operating System :: OS Independent
Requires-Python: >=3.6
License-File: LICENSE
Requires-Dist: openpyxl>=3.1.1
Requires-Dist: pandas>=1.5.3
Requires-Dist: FreeSimpleGUI>=5
Dynamic: author
Dynamic: author-email
Dynamic: classifier
Dynamic: description
Dynamic: description-content-type
Dynamic: home-page
Dynamic: license
Dynamic: license-file
Dynamic: requires-dist
Dynamic: requires-python
Dynamic: summary
